README.md
setup.py
aio_piston/__init__.py
aio_piston/exceptions.py
aio_piston/piston.py
aio_piston/response.py
aio_piston.egg-info/PKG-INFO
aio_piston.egg-info/SOURCES.txt
aio_piston.egg-info/dependency_links.txt
aio_piston.egg-info/requires.txt
aio_piston.egg-info/top_level.txt
aio_piston.egg-info/zip-safe