Metadata-Version: 2.1
Name: aio-piston
Version: 1.0.0
Summary: An unoffical async API wrapper for the piston code execution engine
Home-page: https://github.com/Tom-the-Bomb/aio-piston
Author: Tom-the-Bomb
License: MIT
Project-URL: Repository, https://github.com/Tom-the-Bomb/aio-piston
Project-URL: Issue tracker, https://github.com/Tom-the-Bomb/aio-piston/issues
Platform: UNKNOWN
Classifier: Intended Audience :: Developers
Classifier: Programming Language :: Python
Classifier: Natural Language :: English
Classifier: Programming Language :: Python :: 3.7
Classifier: Programming Language :: Python :: 3.8
Classifier: Programming Language :: Python :: 3.9
Classifier: Topic :: Software Development :: Libraries
Classifier: Topic :: Software Development :: Libraries :: Python Modules
Classifier: Topic :: Utilities
Requires-Python: >=3.7
